Workbook

Sheet LEIA-ME
A1: Dataset de Treinamento de Excel — Finanças (complementar)
A2: Todos os dados são fictícios. A aba Vendas é o dataset original, sem alterações; as demais abas complementam ela.
A4: Aba | B4: Conteúdo | C4: Chave de ligação com Vendas
A5: Vendas | B5: Dataset original (120 vendas, jan–jun/2026). Tabela tblVendas. | C5: —
A6: Produtos | B6: Categoria, fornecedor, preço de lista, custo, margem, lançamento, ativo. | C6: Produto (Vendas!C)
A7: Vendedores | B7: Região, gerente, cargo, admissão, % de comissão, salário base. | C7: Vendedor (Vendas!D)
A8: Centro_Custo | B8: Descrição, área, responsável e meta de receita semestral por Cost Center. | C8: Cost Center (Vendas!H)
A9: Contas_GL | B9: Descrição, tipo e natureza das contas contábeis. GL guardado como TEXTO. | C9: GL (Vendas!I)
A10: Metas | B10: Meta mensal de quantidade e valor por região/produto (jan–jun/2026). | C10: Regiao + Produto + mês (Vendas!A, B, C)
A11: Feriados | B11: Feriados nacionais/pontos facultativos do 1º semestre de 2026. | C11: Data (para dias úteis)
A12: Faixas_Bonus | B12: Tabela de faixas de atingimento x bônus, feita para busca aproximada. | C12: Atingimento de meta
A13: Exercicios | B13: 26 exercícios do básico ao avançado, com célula amarela para sua resposta. | C13: —
A14: Gabarito | B14: Fórmula em PT-BR (texto) e resultado calculado ao vivo de cada exercício. | C14: —
A16: Pegadinhas propositais
A17: • | B17: Vendas!Data está em TEXTO (aaaa-mm-dd), não é data real. Use DATA.VALOR ou curingas para trabalhar com ela.
A18: • | B18: Vendas!GL é TEXTO. Contas_GL!GL também é texto para o PROCV funcionar; se um lado virar número, dá #N/D.
A19: • | B19: Há itens sem vendas (Diego, Fernanda, Marcos; Teams, Dynamics 365; CC400; GL 610004): bom para testar SEERRO e contagens zeradas.
A20: • | B20: As abas novas são Tabelas do Excel (tblProdutos, tblVendedores, tblMetas...). Dá para usar referências estruturadas.
A21: • | B21: As fórmulas do Gabarito estão no Excel em português; internamente o arquivo funciona em qualquer idioma.
A23: Legenda
A24: Célula amarela | B24: Onde você escreve sua resposta (aba Exercicios).

Sheet Vendas
A1: Data | B1: Regiao | C1: Produto | D1: Vendedor | E1: Quantidade | F1: Valor_Unitario | G1: Valor_Total | H1: Cost Center | I1: GL
A2: 2026-01-02 | B2: Sudeste | C2: Copilot | D2: Bruno | E2: 2 | F2: 200 | G2: =E2*F2 -> 400 | H2: CC200 | I2: 610002
A3: 2026-01-03 | B3: Norte | C3: Azure | D3: Carlos | E3: 3 | F3: 300 | G3: =E3*F3 -> 900 | H3: CC300 | I3: 610003
A4: 2026-01-04 | B4: Nordeste | C4: Office 365 | D4: Julia | E4: 4 | F4: 400 | G4: =E4*F4 -> 1600 | H4: CC100 | I4: 610001
A5: 2026-01-05 | B5: Sul | C5: Power BI | D5: Ana | E5: 5 | F5: 100 | G5: =E5*F5 -> 500 | H5: CC200 | I5: 610002
A6: 2026-01-06 | B6: Sudeste | C6: Copilot | D6: Bruno | E6: 1 | F6: 200 | G6: =E6*F6 -> 200 | H6: CC300 | I6: 610003
A7: 2026-01-07 | B7: Norte | C7: Azure | D7: Carlos | E7: 2 | F7: 300 | G7: =E7*F7 -> 600 | H7: CC100 | I7: 610001
A8: 2026-01-08 | B8: Nordeste | C8: Office 365 | D8: Julia | E8: 3 | F8: 400 | G8: =E8*F8 -> 1200 | H8: CC200 | I8: 610002
A9: 2026-01-09 | B9: Sul | C9: Power BI | D9: Ana | E9: 4 | F9: 100 | G9: =E9*F9 -> 400 | H9: CC300 | I9: 610003
A10: 2026-01-10 | B10: Sudeste | C10: Copilot | D10: Bruno | E10: 5 | F10: 200 | G10: =E10*F10 -> 1000 | H10: CC100 | I10: 610001
A11: 2026-01-11 | B11: Norte | C11: Azure | D11: Carlos | E11: 1 | F11: 300 | G11: =E11*F11 -> 300 | H11: CC200 | I11: 610002
A12: 2026-01-12 | B12: Nordeste | C12: Office 365 | D12: Julia | E12: 2 | F12: 400 | G12: =E12*F12 -> 800 | H12: CC300 | I12: 610003
A13: 2026-01-13 | B13: Sul | C13: Power BI | D13: Ana | E13: 3 | F13: 100 | G13: =E13*F13 -> 300 | H13: CC100 | I13: 610001
... A121: 2026-06-21 | B121: Sul | C121: Power BI | D121: Ana | E121: 1 | F121: 100 | G121: =E121*F121 -> 100 | H121: CC300 | I121: 610003

Sheet Produtos
A1: Produto | B1: Categoria | C1: Fornecedor | D1: Preco_Lista | E1: Custo_Unitario | F1: Margem_Pct | G1: Data_Lancamento | H1: Ativo
A2: Copilot | B2: IA | C2: Microsoft | D2: 200 | E2: 130 | F2: =(D2-E2)/D2 -> 0.35 | G2: 44986 | H2: Sim
A3: Azure | B3: Nuvem | C3: Microsoft | D3: 300 | E3: 195 | F3: =(D3-E3)/D3 -> 0.35 | G3: 40210 | H3: Sim
A4: Office 365 | B4: Produtividade | C4: Microsoft | D4: 400 | E4: 240 | F4: =(D4-E4)/D4 -> 0.4 | G4: 40722 | H4: Sim
A5: Power BI | B5: Analytics | C5: Microsoft | D5: 100 | E5: 55 | F5: =(D5-E5)/D5 -> 0.45 | G5: 42209 | H5: Sim
A6: Teams | B6: Produtividade | C6: Microsoft | D6: 150 | E6: 90 | F6: =(D6-E6)/D6 -> 0.4 | G6: 42808 | H6: Sim
A7: Dynamics 365 | B7: ERP/CRM | C7: Microsoft | D7: 500 | E7: 340 | F7: =(D7-E7)/D7 -> 0.32 | G7: 42675 | H7: Não

Sheet Vendedores
A1: Vendedor | B1: Regiao | C1: Produto_Foco | D1: Gerente | E1: Cargo | F1: Data_Admissao | G1: Comissao_Pct | H1: Salario_Base
A2: Bruno | B2: Sudeste | C2: Copilot | D2: Renata Alves | E2: Executivo de Contas Sr | F2: 44270 | G2: 0.04 | H2: 7500
A3: Carlos | B3: Norte | C3: Azure | D3: Marcelo Tavares | E3: Executivo de Contas Pl | F3: 44774 | G3: 0.035 | H3: 6200
A4: Julia | B4: Nordeste | C4: Office 365 | D4: Marcelo Tavares | E4: Executivo de Contas Sr | F4: 43850 | G4: 0.045 | H4: 7800
A5: Ana | B5: Sul | C5: Power BI | D5: Renata Alves | E5: Executivo de Contas Jr | F5: 45418 | G5: 0.03 | H5: 4800
A6: Diego | B6: Sudeste | C6: Teams | D6: Renata Alves | E6: Executivo de Contas Jr | F6: 45698 | G6: 0.03 | H6: 4500
A7: Fernanda | B7: Sul | C7: Dynamics 365 | D7: Renata Alves | E7: Executivo de Contas Pl | F7: 45173 | G7: 0.035 | H7: 6000
A8: Marcos | B8: Norte | C8: Teams | D8: Marcelo Tavares | E8: Executivo de Contas Jr | F8: 45943 | G8: 0.03 | H8: 4500

Sheet Centro_Custo
A1: Cost Center | B1: Descricao | C1: Area | D1: Responsavel | E1: Meta_Receita_Semestre
A2: CC100 | B2: Vendas Corporativas | C2: Comercial | D2: Patricia Lima | E2: 33000
A3: CC200 | B3: Vendas Varejo | C3: Comercial | D3: Rodrigo Nunes | E3: 30000
A4: CC300 | B4: Canais e Parcerias | C4: Comercial | D4: Beatriz Souza | E4: 28500
A5: CC400 | B5: Marketing de Produto | C5: Marketing | D5: Andre Costa | E5: 15000

Sheet Contas_GL
A1: GL | B1: Descricao_GL | C1: Tipo_Conta | D1: Natureza
A2: 610001 | B2: Receita de Licenciamento | C2: Receita | D2: Credora
A3: 610002 | B3: Receita de Serviços em Nuvem | C3: Receita | D3: Credora
A4: 610003 | B4: Receita de Assinaturas | C4: Receita | D4: Credora
A5: 610004 | B5: Receita de Suporte Técnico | C5: Receita | D5: Credora

Sheet Metas
A1: Mes | B1: Regiao | C1: Produto | D1: Meta_Quantidade | E1: Preco_Lista | F1: Meta_Valor
A2: 46023 | B2: Sudeste | C2: Copilot | D2: 13 | E2: =INDEX(Produtos!$D$2:$D$7,MATCH(C2,Produtos!$A$2:$A$7,0)) -> 200 | F2: =D2*E2 -> 2600
A3: 46023 | B3: Norte | C3: Azure | D3: 12 | E3: =INDEX(Produtos!$D$2:$D$7,MATCH(C3,Produtos!$A$2:$A$7,0)) -> 300 | F3: =D3*E3 -> 3600
A4: 46023 | B4: Nordeste | C4: Office 365 | D4: 16 | E4: =INDEX(Produtos!$D$2:$D$7,MATCH(C4,Produtos!$A$2:$A$7,0)) -> 400 | F4: =D4*E4 -> 6400
A5: 46023 | B5: Sul | C5: Power BI | D5: 15 | E5: =INDEX(Produtos!$D$2:$D$7,MATCH(C5,Produtos!$A$2:$A$7,0)) -> 100 | F5: =D5*E5 -> 1500
A6: 46054 | B6: Sudeste | C6: Copilot | D6: 15 | E6: =INDEX(Produtos!$D$2:$D$7,MATCH(C6,Produtos!$A$2:$A$7,0)) -> 200 | F6: =D6*E6 -> 3000
A7: 46054 | B7: Norte | C7: Azure | D7: 14 | E7: =INDEX(Produtos!$D$2:$D$7,MATCH(C7,Produtos!$A$2:$A$7,0)) -> 300 | F7: =D7*E7 -> 4200
A8: 46054 | B8: Nordeste | C8: Office 365 | D8: 13 | E8: =INDEX(Produtos!$D$2:$D$7,MATCH(C8,Produtos!$A$2:$A$7,0)) -> 400 | F8: =D8*E8 -> 5200
A9: 46054 | B9: Sul | C9: Power BI | D9: 13 | E9: =INDEX(Produtos!$D$2:$D$7,MATCH(C9,Produtos!$A$2:$A$7,0)) -> 100 | F9: =D9*E9 -> 1300
A10: 46082 | B10: Sudeste | C10: Copilot | D10: 18 | E10: =INDEX(Produtos!$D$2:$D$7,MATCH(C10,Produtos!$A$2:$A$7,0)) -> 200 | F10: =D10*E10 -> 3600
A11: 46082 | B11: Norte | C11: Azure | D11: 12 | E11: =INDEX(Produtos!$D$2:$D$7,MATCH(C11,Produtos!$A$2:$A$7,0)) -> 300 | F11: =D11*E11 -> 3600
A12: 46082 | B12: Nordeste | C12: Office 365 | D12: 12 | E12: =INDEX(Produtos!$D$2:$D$7,MATCH(C12,Produtos!$A$2:$A$7,0)) -> 400 | F12: =D12*E12 -> 4800
A13: 46082 | B13: Sul | C13: Power BI | D13: 13 | E13: =INDEX(Produtos!$D$2:$D$7,MATCH(C13,Produtos!$A$2:$A$7,0)) -> 100 | F13: =D13*E13 -> 1300
... A25: 46174 | B25: Sul | C25: Power BI | D25: 17 | E25: =INDEX(Produtos!$D$2:$D$7,MATCH(C25,Produtos!$A$2:$A$7,0)) -> 100 | F25: =D25*E25 -> 1700

Sheet Feriados
A1: Data | B1: Feriado | C1: Tipo
A2: 46023 | B2: Confraternização Universal | C2: Nacional
A3: 46069 | B3: Carnaval (segunda) | C3: Ponto facultativo
A4: 46070 | B4: Carnaval (terça) | C4: Ponto facultativo
A5: 46115 | B5: Sexta-feira Santa | C5: Nacional
A6: 46133 | B6: Tiradentes | C6: Nacional
A7: 46143 | B7: Dia do Trabalho | C7: Nacional
A8: 46177 | B8: Corpus Christi | C8: Ponto facultativo

Sheet Faixas_Bonus
A1: Atingimento_Min | B1: Bonus_Pct | C1: Classificacao
A2: 0 | B2: 0 | C2: Abaixo da meta
A3: 0.8 | B3: 0.02 | C3: Próximo da meta
A4: 1 | B4: 0.05 | C4: Meta batida
A5: 1.2 | B5: 0.08 | C5: Superou a meta

Sheet Exercicios
A1: Nº | B1: Nível | C1: Funções-chave | D1: Enunciado | E1: Sua resposta
A2: 1 | B2: Básico | C2: SOMA | D2: Calcule o valor total vendido (soma de Valor_Total).
A3: 2 | B3: Básico | C3: MÉDIA | D3: Qual o valor médio (ticket médio) por venda registrada?
A4: 3 | B4: Básico | C4: MÁXIMO, MÍNIMO | D4: Calcule a amplitude das vendas: maior Valor_Total menos o menor.
A5: 4 | B5: Básico | C5: CONT.VALORES | D5: Quantas vendas (linhas) estão registradas na aba Vendas?
A6: 5 | B6: Básico | C6: SOMASE | D6: Qual o valor total vendido na região Sul?
A7: 6 | B7: Básico | C7: SOMASE | D7: Qual a quantidade total vendida do produto Azure?
A8: 7 | B8: Básico | C8: CONT.SES | D8: Quantas vendas o Bruno fez com Quantidade maior ou igual a 3?
A9: 8 | B9: Intermediário | C9: PROCV | D9: Traga a Categoria do produto da venda da linha 2 (aba Produtos).
A10: 9 | B10: Intermediário | C10: ÍNDICE, CORRESP | D10: Traga o Custo_Unitario do produto da linha 2, usando ÍNDICE + CORRESP (sem PROCV).
A11: 10 | B11: Intermediário | C11: SOMARPRODUTO, SOMASE | D11: Calcule o lucro bruto total: soma de Quantidade × (Valor_Unitario − Custo_Unitario), buscando o custo na aba Produtos.
A12: 11 | B12: Intermediário | C12: SOMASE, PROCV | D12: Calcule a comissão devida ao Bruno: total vendido por ele × Comissao_Pct da aba Vendedores.
A13: 12 | B13: Intermediário | C13: PROCV | D13: Traga a Area do Cost Center da venda da linha 2 (aba Centro_Custo).
... A27: 26 | B27: Prática | C27: Formatação Condicional | D27: Na aba Metas, destaque em vermelho as linhas de Meta_Valor abaixo da média e em verde as acima. Depois, adicione barras de dados em Meta_Quantidade.

Sheet Gabarito
A1: Nº | B1: Nível | C1: Fórmula (Excel PT-BR) | D1: Resultado
A2: 1 | B2: Básico | C2: =SOMA(Vendas!G2:G121) | D2: =SUM(Vendas!$G$2:$G$121) -> 90000
A3: 2 | B3: Básico | C3: =MÉDIA(Vendas!G2:G121) | D3: =AVERAGE(Vendas!$G$2:$G$121) -> 750
A4: 3 | B4: Básico | C4: =MÁXIMO(Vendas!G2:G121)-MÍNIMO(Vendas!G2:G121) | D4: =MAX(Vendas!$G$2:$G$121)-MIN(Vendas!$G$2:$G$121) -> 1900
A5: 4 | B5: Básico | C5: =CONT.VALORES(Vendas!A2:A121) | D5: =COUNTA(Vendas!$A$2:$A$121) -> 120
A6: 5 | B6: Básico | C6: =SOMASE(Vendas!B2:B121;"Sul";Vendas!G2:G121) | D6: =SUMIF(Vendas!$B$2:$B$121,"Sul",Vendas!$G$2:$G$121) -> 9000
A7: 6 | B7: Básico | C7: =SOMASE(Vendas!C2:C121;"Azure";Vendas!E2:E121) | D7: =SUMIF(Vendas!$C$2:$C$121,"Azure",Vendas!$E$2:$E$121) -> 90
A8: 7 | B8: Básico | C8: =CONT.SES(Vendas!D2:D121;"Bruno";Vendas!E2:E121;">=3") | D8: =COUNTIFS(Vendas!$D$2:$D$121,"Bruno",Vendas!$E$2:$E$121,">=3") -> 18
A9: 8 | B9: Intermediário | C9: =PROCV(Vendas!C2;Produtos!$A$2:$H$7;2;FALSO) | D9: =VLOOKUP(Vendas!C2,Produtos!$A$2:$H$7,2,FALSE()) -> IA
A10: 9 | B10: Intermediário | C10: =ÍNDICE(Produtos!$E$2:$E$7;CORRESP(Vendas!C2;Produtos!$A$2:$A$7;0)) | D10: =INDEX(Produtos!$E$2:$E$7,MATCH(Vendas!C2,Produtos!$A$2:$A$7,0)) -> 130
A11: 10 | B11: Intermediário | C11: =SOMARPRODUTO(Vendas!E2:E121*(Vendas!F2:F121-SOMASE(Produtos!A2:A7;Vendas!C2:C121;Produtos!E2:E7))) | D11: =SUMPRODUCT(Vendas!$E$2:$E$121*(Vendas!$F$2:$F$121-SUMIF(Produtos!$A$2:$A$7,Vendas!$C$2:$C$121,Produtos!$E$2:$E$7))) -> 34200
A12: 11 | B12: Intermediário | C12: =SOMASE(Vendas!D2:D121;"Bruno";Vendas!G2:G121)*PROCV("Bruno";Vendedores!A2:H8;7;FALSO) | D12: =SUMIF(Vendas!$D$2:$D$121,"Bruno",Vendas!$G$2:$G$121)*VLOOKUP("Bruno",Vendedores!$A$2:$H$8,7,FALSE()) -> 720
A13: 12 | B13: Intermediário | C13: =PROCV(Vendas!H2;Centro_Custo!$A$2:$E$5;3;FALSO) | D13: =VLOOKUP(Vendas!H2,Centro_Custo!$A$2:$E$5,3,FALSE()) -> Comercial
A14: 13 | B14: Intermediário | C14: =PROCV(Vendas!I2;Contas_GL!$A$2:$D$5;2;FALSO) | D14: =VLOOKUP(Vendas!I2,Contas_GL!$A$2:$D$5,2,FALSE()) -> Receita de Serviços em Nuvem
A15: 14 | B15: Intermediário | C15: =SOMASES(Vendas!G2:G121;Vendas!A2:A121;"2026-01*") | D15: =SUMIFS(Vendas!$G$2:$G$121,Vendas!$A$2:$A$121,"2026-01*") -> 15000
A16: 15 | B16: Intermediário | C16: =MÊS(DATA.VALOR(Vendas!A2)) | D16: =MONTH(DATEVALUE(Vendas!A2)) -> 1
A17: 16 | B17: Intermediário | C17: =SEERRO(PROCV("Paulo";Vendedores!A2:H8;7;FALSO);"Não cadastrado") | D17: =IFERROR(VLOOKUP("Paulo",Vendedores!$A$2:$H$8,7,FALSE()),"Não cadastrado") -> Não cadastrado
A18: 17 | B18: Intermediário | C18: =SE(Vendas!G4>=1000;"Alta";SE(Vendas!G4>=500;"Média";"Baixa")) | D18: =IF(Vendas!G4>=1000,"Alta",IF(Vendas!G4>=500,"Média","Baixa")) -> Alta
A19: 18 | B19: Avançado | C19: =SOMASES(Vendas!G2:G121;Vendas!B2:B121;"Sudeste";Vendas!A2:A121;"2026-01*")/SOMASES(Metas!F2:F25;Metas!B2:B25;"Sudeste";Metas!A2:A25;DATA(2026;1;1)) | D19: =SUMIFS(Vendas!$G$2:$G$121,Vendas!$B$2:$B$121,"Sudeste",Vendas!$A$2:$A$121,"2026-01*")/SUMIFS(Metas!$F$2:$F$25,Metas!$B$2:$B$25,"Sudeste",Metas!$A$2:$A$25,DATE(2026,1,1)) -> 1.1538462
A20: 19 | B20: Avançado | C20: =PROCV(<resultado do exercício 18>;Faixas_Bonus!A2:C5;2;VERDADEIRO) | D20: =VLOOKUP(D19,Faixas_Bonus!$A$2:$C$5,2,TRUE()) -> 0.05
A21: 20 | B21: Avançado | C21: =SOMASE(Vendas!B2:B121;"Nordeste";Vendas!G2:G121)/SOMA(Vendas!G2:G121) | D21: =SUMIF(Vendas!$B$2:$B$121,"Nordeste",Vendas!$G$2:$G$121)/SUM(Vendas!$G$2:$G$121) -> 0.4
A22: 21 | B22: Avançado | C22: =SOMARPRODUTO(SOMASE(Vendas!C2:C121;Produtos!A2:A7;Vendas!G2:G121)*(Produtos!B2:B7="Produtividade")) | D22: =SUMPRODUCT(SUMIF(Vendas!$C$2:$C$121,Produtos!$A$2:$A$7,Vendas!$G$2:$G$121)*(Produtos!$B$2:$B$7="Produtividade")) -> 36000
A23: 22 | B23: Avançado | C23: =1+SOMARPRODUTO(--(SOMASE(Vendas!D2:D121;Vendedores!A2:A8;Vendas!G2:G121)>SOMASE(Vendas!D2:D121;"Bruno";Vendas!G2:G121))) | D23: =1+SUMPRODUCT(--(SUMIF(Vendas!$D$2:$D$121,Vendedores!$A$2:$A$8,Vendas!$G$2:$G$121)>SUMIF(Vendas!$D$2:$D$121,"Bruno",Vendas!$G$2:$G$121))) -> 3
A24: 23 | B24: Avançado | C24: =DIATRABALHOTOTAL(DATA(2026;1;1);DATA(2026;1;31);Feriados!A2:A8) | D24: =NETWORKDAYS(DATE(2026,1,1),DATE(2026,1,31),Feriados!$A$2:$A$8) -> 21
A25: 24 | B25: Avançado | C25: =SOMASE(Vendas!H2:H121;"CC200";Vendas!G2:G121)/PROCV("CC200";Centro_Custo!A2:E5;5;FALSO) | D25: =SUMIF(Vendas!$H$2:$H$121,"CC200",Vendas!$G$2:$G$121)/VLOOKUP("CC200",Centro_Custo!$A$2:$E$5,5,FALSE()) -> 1.08
A26: 25 | B26: Prática | C26: Inserir > Tabela Dinâmica > origem: tblVendas. Arraste Regiao para Linhas e Valor_Total para Valores. | D26: (prática – sem fórmula)
A27: 26 | B27: Prática | C27: Página Inicial > Formatação Condicional > Regras de Primeiros/Últimos > Acima/Abaixo da Média. | D27: (prática – sem fórmula)
